Metadata-Version: 1.0
Name: basic-distributions-udacity-exercise
Version: 0.1
Summary: Gaussian and Binomial distributions
Home-page: UNKNOWN
Author: Jhoann Sebastian Pabon Barona
Author-email: UNKNOWN
License: UNKNOWN
Platform: UNKNOWN
